autoplot/__init__.py
autoplot/dtaler/__init__.py
autoplot/extensions/__init__.py
autoplot/extensions/autoplot_display.py
autoplot/extensions/toast.py
autoplot/plotter/__init__.py
autoplot/plotter/range_selector_utils.py
autoplot/plotter/trace.py
autoplot/plugins/__init__.py
autoplot/plugins/interactive_legend.py
autoplot/plugins/line_utils.py
autoplot/plugins/range_selector_buttons.py
autoplot/plugins/save_image_buttons.py
autoplot/plugins/time_series_tooltip.py
autoplot/plugins/bundles/interactiveLegend.js
autoplot/plugins/bundles/rangeSelectorButtons.js
autoplot/plugins/bundles/saveImageButtons.js
autoplot/plugins/bundles/timeSeriesTooltip.js
autoplot/utils/__init__.py
autoplot/utils/constants.py
autoplot/view_manager/__init__.py
autoplot/view_manager/variable_utils.py
jupyterlab_autoplot-0.5.0.dist-info/METADATA
jupyterlab_autoplot-0.5.0.dist-info/WHEEL
jupyterlab_autoplot-0.5.0.dist-info/top_level.txt
jupyterlab_autoplot-0.5.0.dist-info/RECORD
