Metadata-Version: 2.1
Name: jupyterlab-autoplot
Version: 0.5.0
Summary: The IPython component for the Autoplot JupyterLab extension.
Home-page: https://github.com/man-group/jupyterlab-autoplot
Author: Man Alpha Technology
Author-email: ManAlphaTech@man.com
License: BSD 3-Clause
Keywords: jupyter,jupyterlab,matplotlib,mpld3,time series
Classifier: Programming Language :: Python :: 3
Classifier: License :: OSI Approved :: BSD License
Classifier: Operating System :: OS Independent
Classifier: Framework :: Jupyter
Requires-Python: >=3.6
Requires-Dist: ipywidgets
Requires-Dist: ipython
Requires-Dist: numpy
Requires-Dist: pandas
Requires-Dist: matplotlib
Requires-Dist: mpld3
Requires-Dist: dtale (>=2.16.0)
